signate/__init__.py
signate/cli.py
signate/info.py
swagger_client/__init__.py
swagger_client/api_client.py
swagger_client/configuration.py
swagger_client/rest.py
swagger_client/api/__init__.py
swagger_client/api/default_api.py
swagger_client/models/__init__.py
swagger_client/models/competition.py
swagger_client/models/competitions.py
swagger_client/models/download.py
swagger_client/models/downloads.py
swagger_client/models/error.py
swagger_client/models/file.py
swagger_client/models/files.py
swagger_client/models/success.py
swagger_client/models/token.py
signate-9.9.10.dist-info/LICENSE
signate-9.9.10.dist-info/METADATA
signate-9.9.10.dist-info/WHEEL
signate-9.9.10.dist-info/entry_points.txt
signate-9.9.10.dist-info/top_level.txt
signate-9.9.10.dist-info/RECORD
