Metadata-Version: 2.1
Name: signate
Version: 9.9.10
Summary: SIGNATE CLI
Home-page: https://github.com/signatelab/signate-cli
Author: SIGNATE Inc.
License: Apache 2.0
Keywords: signate,signate-cli
Requires-Python: >=3.6
License-File: LICENSE
Requires-Dist: click
Requires-Dist: tabulate
Requires-Dist: wget
Requires-Dist: urllib3 (>=1.26.7)
Requires-Dist: six (>=1.16)
Requires-Dist: certifi
Requires-Dist: python-dateutil
